Metadata-Version: 2.0
Name: todone
Version: 0.0.2
Summary: Todo list manager and agenda
Home-page: https://github.com/safnuk/todone
Author: Brad Safnuk
Author-email: safnuk@gmail.com
License: MIT
Platform: UNKNOWN
Classifier: Programming Language :: Python
Classifier: Programming Language :: Python :: 3
Classifier: Development Status :: 1 - Planning
Classifier: License :: OSI Approved :: MIT License
Classifier: Operating System :: OS Independent
Requires-Dist: peewee
Requires-Dist: python-dateutil
